generator_emails/__init__.py
generator_emails/generator_emails.py
generator_emails-0.1.0.dist-info/LICENSE
generator_emails-0.1.0.dist-info/METADATA
generator_emails-0.1.0.dist-info/WHEEL
generator_emails-0.1.0.dist-info/top_level.txt
generator_emails-0.1.0.dist-info/RECORD
