Metadata-Version: 2.2
Name: generator-emails
Version: 0.1.0
Summary: Generator_emails - Unique Email Address Generator 🚀
Home-page: https://github.com/yourusername/generator-names
Author: Misha
Author-email: bobyyy239@gmail.com
License: MIT
Classifier: Programming Language :: Python :: 3
Classifier: License :: OSI Approved :: MIT License
Classifier: Operating System :: OS Independent
Requires-Python: >=3.6
License-File: LICENSE
Requires-Dist: generator-names>=0.2.0
Dynamic: author
Dynamic: author-email
Dynamic: classifier
Dynamic: description
Dynamic: description-content-type
Dynamic: home-page
Dynamic: license
Dynamic: requires-dist
Dynamic: requires-python
Dynamic: summary
